Tables/__about__.py
Tables/__init__.py
Tables/general/__init__.py
Tables/general/library_attributes.py
Tables/keywords/__init__.py
Tables/keywords/configuration.py
Tables/keywords/excel.py
Tables/keywords/getter.py
Tables/keywords/modifier.py
Tables/keywords/writer.py
Tables/utils/__init__.py
Tables/utils/file_access.py
Tables/utils/file_reader.py
Tables/utils/file_system.py
Tables/utils/file_writer.py
Tables/utils/settings.py
robotframework_tablelibrary-0.1.3.dist-info/METADATA
robotframework_tablelibrary-0.1.3.dist-info/WHEEL
robotframework_tablelibrary-0.1.3.dist-info/licenses/LICENSE
robotframework_tablelibrary-0.1.3.dist-info/RECORD
