Metadata-Version: 2.4
Name: robotframework-tablelibrary
Version: 0.1.3
Summary: A Robot Framework library providing generic table keywords for several table file type like csv or excel.
Project-URL: Homepage, https://github.com/imbus/robotframework-tablelibrary
Project-URL: Documentation, https://github.com/imbus/robotframework-tablelibrary#readme
Project-URL: Contributing, https://github.com/imbus/robotframework-tablelibrary/blob/main/DEVELOPMENT.md
Project-URL: Issues, https://github.com/imbus/robotframework-tablelibrary/issues
Project-URL: KeywordDocumentation, https://imbus.github.io/robotframework-tablelibrary/keywords.html
Author: imbus AG
Maintainer-email: Marvin Klerx <marvinklerx20@gmail.com>
License: Apache-2.0
License-File: LICENSE
Classifier: Development Status :: 3 - Alpha
Classifier: Programming Language :: Python
Classifier: Programming Language :: Python :: 3.10
Classifier: Programming Language :: Python :: 3.11
Classifier: Programming Language :: Python :: 3.12
Requires-Python: >=3.10
Requires-Dist: openpyxl
Requires-Dist: overrides
Requires-Dist: pandas
Requires-Dist: pyarrow
Requires-Dist: robotframework-assertion-engine
Requires-Dist: robotframework-pythonlibcore
Requires-Dist: robotframework>=5.0.1
Requires-Dist: xlrd
Provides-Extra: dev
Requires-Dist: hatch; extra == 'dev'
Requires-Dist: mypy; extra == 'dev'
Requires-Dist: pre-commit; extra == 'dev'
Requires-Dist: pytest; extra == 'dev'
Requires-Dist: robotframework-robocop; extra == 'dev'
Requires-Dist: ruff; extra == 'dev'
